geomapdemo/__init__.py
geomapdemo/chart.py
geomapdemo/foliumap.py
geomapdemo/geomapdemo.py
geomapdemo/plot.py
geomapdemo-0.3.4.dist-info/LICENSE
geomapdemo-0.3.4.dist-info/METADATA
geomapdemo-0.3.4.dist-info/WHEEL
geomapdemo-0.3.4.dist-info/dependency_links.txt
geomapdemo-0.3.4.dist-info/top_level.txt
geomapdemo-0.3.4.dist-info/RECORD
